PFDiscord/PFDiscord.py
PFDiscord/__init__.py
PFDiscord/conversation.py
PFDiscord/initialize.py
PFDiscord/message_handlers.py
PFDiscord/tokenGPT.py
PFDiscord/utils.py
PFDiscord/web_utils.py
PFDiscord-1.0.5.dist-info/LICENSE
PFDiscord-1.0.5.dist-info/METADATA
PFDiscord-1.0.5.dist-info/WHEEL
PFDiscord-1.0.5.dist-info/top_level.txt
PFDiscord-1.0.5.dist-info/RECORD
