Metadata-Version: 2.1
Name: PFDiscord
Version: 1.0.5
Summary: OpenAI GPT, driven by Discord
Home-page: https://github.com/Digital-Heresy/PFDiscord
Author: Digital Heretic
Author-email: agiheretic@proton.me
License: AGPL-3.0
Requires-Python: >=3.10
License-File: LICENSE
Requires-Dist: openai
Requires-Dist: PyYAML
Requires-Dist: httpx
Requires-Dist: beautifulsoup4
Requires-Dist: typing
Requires-Dist: validators
Requires-Dist: discord.py
Requires-Dist: tiktoken
